kyvern_shield/__init__.py
kyvern_shield/client.py
kyvern_shield/py.typed
kyvern_shield-0.1.0.dist-info/METADATA
kyvern_shield-0.1.0.dist-info/WHEEL
kyvern_shield-0.1.0.dist-info/licenses/LICENSE
kyvern_shield-0.1.0.dist-info/RECORD
