Metadata-Version: 2.4
Name: kyvern-shield
Version: 0.1.0
Summary: Sovereign AI Security SDK - Protect AI agents from prompt injection and wallet drains
Project-URL: Homepage, https://kyvernlabs.com
Project-URL: Documentation, https://docs.kyvernlabs.com
Project-URL: Repository, https://github.com/kyvernlabs/shield-sdk-python
Project-URL: Issues, https://github.com/kyvernlabs/shield-sdk-python/issues
Author-email: Kyvern Labs <hello@kyvernlabs.com>
License: MIT
License-File: LICENSE
Keywords: agents,ai,firewall,security,solana,transaction,web3
Classifier: Development Status :: 4 - Beta
Classifier: Intended Audience :: Developers
Classifier: License :: OSI Approved :: MIT License
Classifier: Operating System :: OS Independent
Classifier: Programming Language :: Python :: 3
Classifier: Programming Language :: Python :: 3.9
Classifier: Programming Language :: Python :: 3.10
Classifier: Programming Language :: Python :: 3.11
Classifier: Programming Language :: Python :: 3.12
Classifier: Topic :: Security
Classifier: Topic :: Software Development :: Libraries :: Python Modules
Requires-Python: >=3.9
Requires-Dist: httpx>=0.25.0
Requires-Dist: pydantic>=2.0.0
Provides-Extra: dev
Requires-Dist: mypy>=1.8.0; extra == 'dev'
Requires-Dist: pytest-asyncio>=0.23.0; extra == 'dev'
Requires-Dist: pytest-httpx>=0.30.0; extra == 'dev'
Requires-Dist: pytest>=8.0.0; extra == 'dev'
Requires-Dist: ruff>=0.2.0; extra == 'dev'
